autonomize/__init__.py
autonomize/core/__init__.py
autonomize/core/base_client.py
autonomize/core/credential.py
autonomize/exceptions/__init__.py
autonomize/exceptions/core/__init__.py
autonomize/exceptions/core/credentials.py
autonomize/py.typed
autonomize/types/__init__.py
autonomize/types/core/__init__.py
autonomize/types/core/base_client.py
autonomize/types/core/credential.py
autonomize/utils/__init__.py
autonomize/utils/logger.py
autonomize_core-0.1.16.dist-info/METADATA
autonomize_core-0.1.16.dist-info/WHEEL
autonomize_core-0.1.16.dist-info/licenses/LICENSE
autonomize_core-0.1.16.dist-info/RECORD
