Metadata-Version: 2.4
Name: autonomize-core
Version: 0.1.16
Summary: Autonomize Core contains the unified authentication source to access platform.
License: Proprietary
License-File: LICENSE
Author: Varun Prakash
Author-email: varun.prakash@autonomize.ai
Requires-Python: >=3.12,<4.0
Classifier: Development Status :: 3 - Alpha
Classifier: Intended Audience :: Developers
Classifier: License :: Other/Proprietary License
Classifier: Natural Language :: English
Classifier: Operating System :: OS Independent
Classifier: Programming Language :: Python :: 3
Classifier: Programming Language :: Python :: 3.12
Classifier: Programming Language :: Python :: 3.13
Classifier: Programming Language :: Python :: 3.14
Classifier: Topic :: Scientific/Engineering :: Artificial Intelligence
Classifier: Topic :: Software Development :: Libraries :: Application Frameworks
Classifier: Topic :: Software Development :: Libraries :: Python Modules
Classifier: Topic :: Text Processing
Classifier: Typing :: Typed
Requires-Dist: httpx (>=0.28.0)
Project-URL: Documentation, https://github.com/autonomize-ai/autonomize-core
Project-URL: Homepage, https://github.com/autonomize-ai/autonomize-core
Project-URL: Repository, https://github.com/autonomize-ai/autonomize-core
